asyncapi_schema_pydantic/__init__.py
asyncapi_schema_pydantic/v2_3_0/__init__.py
asyncapi_schema_pydantic/v2_3_0/amqp1_bindings.py
asyncapi_schema_pydantic/v2_3_0/amqp_bindings.py
asyncapi_schema_pydantic/v2_3_0/anypoint_mq_bindings.py
asyncapi_schema_pydantic/v2_3_0/async_api.py
asyncapi_schema_pydantic/v2_3_0/async_api_base.py
asyncapi_schema_pydantic/v2_3_0/channel.py
asyncapi_schema_pydantic/v2_3_0/channel_bindings.py
asyncapi_schema_pydantic/v2_3_0/components.py
asyncapi_schema_pydantic/v2_3_0/contact.py
asyncapi_schema_pydantic/v2_3_0/correlation_id.py
asyncapi_schema_pydantic/v2_3_0/external_documentation.py
asyncapi_schema_pydantic/v2_3_0/http_bindings.py
asyncapi_schema_pydantic/v2_3_0/ibm_mq_bindings.py
asyncapi_schema_pydantic/v2_3_0/info.py
asyncapi_schema_pydantic/v2_3_0/jms_bindings.py
asyncapi_schema_pydantic/v2_3_0/json_schema.py
asyncapi_schema_pydantic/v2_3_0/kafka_bindings.py
asyncapi_schema_pydantic/v2_3_0/license.py
asyncapi_schema_pydantic/v2_3_0/mercure_bindings.py
asyncapi_schema_pydantic/v2_3_0/message.py
asyncapi_schema_pydantic/v2_3_0/message_bindings.py
asyncapi_schema_pydantic/v2_3_0/message_example.py
asyncapi_schema_pydantic/v2_3_0/message_trait.py
asyncapi_schema_pydantic/v2_3_0/mqtt5_bindings.py
asyncapi_schema_pydantic/v2_3_0/mqtt_bindings.py
asyncapi_schema_pydantic/v2_3_0/nats_bindings.py
asyncapi_schema_pydantic/v2_3_0/oauth_flows.py
asyncapi_schema_pydantic/v2_3_0/operation.py
asyncapi_schema_pydantic/v2_3_0/operation_bindings.py
asyncapi_schema_pydantic/v2_3_0/operation_trait.py
asyncapi_schema_pydantic/v2_3_0/parameter.py
asyncapi_schema_pydantic/v2_3_0/redis_bindings.py
asyncapi_schema_pydantic/v2_3_0/reference.py
asyncapi_schema_pydantic/v2_3_0/schema.py
asyncapi_schema_pydantic/v2_3_0/security_requirement.py
asyncapi_schema_pydantic/v2_3_0/security_scheme.py
asyncapi_schema_pydantic/v2_3_0/server.py
asyncapi_schema_pydantic/v2_3_0/server_bindings.py
asyncapi_schema_pydantic/v2_3_0/server_variable.py
asyncapi_schema_pydantic-1.0.1.dist-info/LICENSE
asyncapi_schema_pydantic-1.0.1.dist-info/METADATA
asyncapi_schema_pydantic-1.0.1.dist-info/WHEEL
asyncapi_schema_pydantic-1.0.1.dist-info/top_level.txt
asyncapi_schema_pydantic-1.0.1.dist-info/RECORD
