Metadata-Version: 2.1
Name: asyncapi-schema-pydantic
Version: 1.0.1
Summary: AsyncAPI (v2) specification schema as pydantic class
Home-page: https://github.com/albertnadal/asyncapi-schema-pydantic
Author: Albert Nadal Garriga
License: MIT
Classifier: License :: OSI Approved :: MIT License
Classifier: Programming Language :: Python :: 3
Classifier: Programming Language :: Python :: 3.6
Classifier: Operating System :: OS Independent
Requires-Python: >=3.7
License-File: LICENSE
Requires-Dist: pydantic >=1.8.2
Requires-Dist: PyYAML ~=6.0
